{
  "pins": [
    {
      "id": "71bc426b-d202-4063-b77a-f0c982c2fa93",
      "pins": "8902",
      "usersID": [
        {
          "id": "lxr7e98ivn30ls0wfw"
        }
      ],
      "creator": {},
      "sesionIniciada": true
    },
    {
      "id": "e4b29837-1585-4db9-b940-b2265a204a04",
      "pins": "9125",
      "usersID": [],
      "creator": {},
      "sesionIniciada": false
    },
    {
      "id": "b59f5318-d63f-4c30-8d7e-38c9cf1b9e2d",
      "pins": "2381",
      "usersID": [],
      "creator": {},
      "sesionIniciada": false
    },
    {
      "id": "f9996319-0cd4-44f4-b191-55db5b99a14b",
      "pins": "9673",
      "usersID": [],
      "creator": {},
      "sesionIniciada": false
    },
    {
      "id": "4fb4f03d-d9c7-4cb3-ab4a-fb436fbe1c3b",
      "pins": "2074",
      "usersID": [],
      "creator": {},
      "sesionIniciada": false
    },
    {
      "id": "18a1864b-ffa2-4150-9111-2e0cc103e90d",
      "pins": "4571",
      "usersID": [],
      "creator": {},
      "sesionIniciada": false
    },
    {
      "id": "9f6a303f-442e-44d1-854f-e670a99ca626",
      "pins": "5968",
      "usersID": [],
      "creator": {},
      "sesionIniciada": false
    },
    {
      "id": "780c49e3-5bca-4de9-8c33-93c54ef80a47",
      "pins": "3061",
      "usersID": [],
      "creator": {},
      "sesionIniciada": false
    },
    {
      "id": "701cb7ca-d16e-4321-973a-fd726e15c458",
      "pins": "7703",
      "usersID": [],
      "creator": {},
      "sesionIniciada": false
    },
    {
      "id": "492a6056-324f-49bc-bd16-658489b30c4e",
      "pins": "4963",
      "usersID": [],
      "creator": {},
      "sesionIniciada": false
    },
    {
      "id": "fd419124-5d5c-4254-96ab-c3358f877d18",
      "pins": "8664",
      "usersID": [],
      "creator": {},
      "sesionIniciada": false
    },
    {
      "id": "9333055d-505d-482b-be3f-0201169fcf6e",
      "pins": "3779",
      "usersID": [],
      "creator": {},
      "sesionIniciada": false
    },
    {
      "id": "4c5cee1a-53ea-4e56-9093-b02dc0f2655a",
      "pins": "2015",
      "usersID": [],
      "creator": {},
      "sesionIniciada": false
    },
    {
      "id": "152e94a1-e5e5-44fb-8330-ff78d204cfee",
      "pins": "4548",
      "usersID": [],
      "creator": {},
      "sesionIniciada": false
    },
    {
      "id": "6e78bb78-9a8d-4ff5-a84e-e8923a14b6de",
      "pins": "8645",
      "usersID": [],
      "creator": {},
      "sesionIniciada": false
    },
    {
      "id": "ae80ba48-fd71-4c94-813b-21c37f40f965",
      "pins": "9923",
      "usersID": [],
      "creator": {},
      "sesionIniciada": false
    },
    {
      "id": "1cdbabcc-a7f7-44d0-a918-293473c73a57",
      "pins": "2255",
      "usersID": [],
      "creator": {},
      "sesionIniciada": false
    },
    {
      "id": "2efea8da-3503-469b-9f09-0bd03c8fe8e0",
      "pins": "8311",
      "usersID": [],
      "creator": {},
      "sesionIniciada": false
    },
    {
      "id": "f428c1aa-0d0a-4e25-813d-123023cc8f8e",
      "pins": "3539",
      "usersID": [
        {
          "id": "lxwr2rvja0cos6dx8c"
        }
      ],
      "creator": {},
      "sesionIniciada": true
    },
    {
      "id": "d79c9bc6-551d-4b4e-be2a-fd691b94ba21",
      "pins": "1557",
      "usersID": [],
      "creator": {},
      "sesionIniciada": true
    },
    {
      "id": "58bc8eb7-b85e-4942-8330-e0e12becd3a0",
      "pins": "1504",
      "usersID": [
        {
          "id": "lxwrmf1b2xpn4l04tf"
        }
      ],
      "creator": {},
      "sesionIniciada": true
    },
    {
      "id": "f769fbc0-a406-4355-be94-c04a9602ed51",
      "pins": "4750",
      "usersID": [
        {
          "id": "lxwsfgc853vi37o78y"
        }
      ],
      "creator": {},
      "sesionIniciada": false
    },
    {
      "id": "3c60a922-5d6d-4de0-9473-689e29d95008",
      "pins": "9782",
      "usersID": [
        {
          "id": "lxwsiiklc60yi1utwu"
        }
      ],
      "creator": {},
      "sesionIniciada": true
    },
    {
      "id": "2c08cacb-2c3d-492a-9b9a-b387ae72fe61",
      "pins": "5683",
      "usersID": [
        {
          "id": "lxwsm84unka9rqk4yt"
        }
      ],
      "creator": {},
      "sesionIniciada": true
    },
    {
      "id": "74e18004-1b48-4ec7-9432-bdf98a6efd73",
      "pins": "4386",
      "usersID": [
        {
          "id": "lxwsnv01ajspjwsuel"
        }
      ],
      "creator": {},
      "sesionIniciada": true
    },
    {
      "id": "90731a8f-969a-4ae2-854f-b5332263636a",
      "pins": "8187",
      "usersID": [
        {
          "id": "lxwsqyygl5vmtwrjrj"
        }
      ],
      "creator": {},
      "sesionIniciada": true
    },
    {
      "id": "002037ea-8e2c-4fef-b5f5-8a1152a9f0cf",
      "pins": "5313",
      "usersID": [
        {
          "id": "lxwwhvn5nrfd09w06w"
        }
      ],
      "creator": {},
      "sesionIniciada": true
    },
    {
      "id": "9f3844b9-1170-44b8-b635-95f64bc581d2",
      "pins": "7026",
      "usersID": [
        {
          "id": "lxwwllr7f16im1kees"
        }
      ],
      "creator": {},
      "sesionIniciada": true
    },
    {
      "id": "e81103b0-e876-4bfc-a051-488ef5c747e9",
      "pins": "3700",
      "usersID": [],
      "creator": {},
      "sesionIniciada": true
    },
    {
      "id": "28c385d2-3aaf-41da-a3ba-2e97790019ad",
      "pins": "4967",
      "usersID": [],
      "creator": {},
      "sesionIniciada": true
    },
    {
      "id": "3e0f629d-e542-4a0a-be26-8c56bc32056e",
      "pins": "4540",
      "usersID": [],
      "creator": {},
      "sesionIniciada": true
    },
    {
      "id": "bc47df4e-088d-4fae-873b-f5b80492d64a",
      "pins": "1001",
      "usersID": [],
      "creator": {},
      "sesionIniciada": true
    },
    {
      "id": "6df0212f-05e3-4d97-8e89-e22251316c38",
      "pins": "8540",
      "usersID": [],
      "creator": {},
      "sesionIniciada": true
    },
    {
      "id": "32bc57fc-519d-4fab-87a3-74bfff4a80c5",
      "pins": "4551",
      "usersID": [],
      "creator": {},
      "sesionIniciada": true
    },
    {
      "id": "dd95193c-1c31-40fb-8826-39ff62516cb5",
      "pins": "7015",
      "usersID": [],
      "creator": {},
      "sesionIniciada": true
    },
    {
      "id": "3571b09d-9c6b-4d0e-9445-0b9057d4e936",
      "pins": "6759",
      "usersID": [
        {
          "id": "lxwxsa87a7e6ylvggf"
        }
      ],
      "creator": {},
      "sesionIniciada": true
    },
    {
      "id": "4a1d481f-953c-4a0b-9d47-e94b0a341297",
      "pins": "3813",
      "usersID": [
        {
          "id": "lxwy5putv3o6fhywue"
        }
      ],
      "creator": {},
      "sesionIniciada": true
    },
    {
      "id": "7d356938-8de2-4945-bfa2-e5b1f7b85630",
      "pins": "5854",
      "usersID": [
        {
          "id": "lxwy8v79494xzm6z9l"
        }
      ],
      "creator": {},
      "sesionIniciada": true
    },
    {
      "id": "796b7c94-d248-4683-a05b-3a2f35db1527",
      "pins": "1484",
      "usersID": [
        {
          "id": "lxwyaey0cerpu52vmp"
        }
      ],
      "creator": {},
      "sesionIniciada": true
    },
    {
      "id": "ea70cae9-3a03-454e-9854-53663a15ebf6",
      "pins": "2951",
      "usersID": [
        {
          "id": "lxwyjlj4dnx2u29bh5"
        }
      ],
      "creator": {},
      "sesionIniciada": true
    },
    {
      "id": "cb10ce94-ae89-47e4-918d-7ec400ae39bd",
      "pins": "2346",
      "usersID": [
        {
          "id": "lxwypy29hwq5al43cj"
        }
      ],
      "creator": {},
      "sesionIniciada": true
    },
    {
      "id": "a268f329-4a0b-41f4-bf81-440553e6cc85",
      "pins": "4728",
      "usersID": [
        {
          "id": "lxwyu36ol02lkkz03e"
        }
      ],
      "creator": {},
      "sesionIniciada": true
    },
    {
      "id": "0ad9c4fb-8b7b-424e-b794-d45950e56686",
      "pins": "2331",
      "usersID": [
        {
          "id": "lxwyxiqasf38zx586c"
        },
        {
          "id": "lxwyyf81biqywm0f2z"
        }
      ],
      "creator": {},
      "sesionIniciada": true
    },
    {
      "id": "57f37237-af3d-4cac-9fe0-2d9b37003639",
      "pins": "8848",
      "usersID": [
        {
          "id": "lxwz5ag57rr8rhfn3g"
        },
        {
          "id": "lxwz5v1py2zneohhan"
        }
      ],
      "creator": {},
      "sesionIniciada": true
    },
    {
      "id": "e2590cdd-cad5-4d5c-9c9e-42b95518a92c",
      "pins": "2348",
      "usersID": [
        {
          "id": "lxwz6rndrfbeyvhn14"
        }
      ],
      "creator": {},
      "sesionIniciada": true
    },
    {
      "id": "81176915-2abf-4924-80eb-29c9f296c83e",
      "pins": "6933",
      "usersID": [
        {
          "id": "lxwz8fh5qxexlc0dpd"
        }
      ],
      "creator": {},
      "sesionIniciada": true
    },
    {
      "id": "136dd09a-1467-4675-ba04-cfd5df9a25ce",
      "pins": "9960",
      "usersID": [
        {
          "id": "lxwze3gvg1swmjzcgv"
        }
      ],
      "creator": {},
      "sesionIniciada": true
    }
  ],
  "users": [
    {
      "id": "lxr7s1ew9amnk9cnsb",
      "username": "eeee",
      "password": "lxr7s1ew9amnk9cnsb",
      "firstname": "",
      "lastname": "",
      "phonenumber": "",
      "email": "",
      "usertype": "Alumno",
      "membership": ""
    },
    {
      "id": "lxwq3e167pfmok1a82",
      "username": "maaaa",
      "password": "lxwq3e167pfmok1a82",
      "firstname": "",
      "lastname": "",
      "phonenumber": "",
      "email": "",
      "usertype": "Alumno",
      "membership": ""
    },
    {
      "id": "lxwq6kagkz5s3n8nbz",
      "username": "asdadasas",
      "password": "lxwq6kagkz5s3n8nbz",
      "firstname": "",
      "lastname": "",
      "phonenumber": "",
      "email": "",
      "usertype": "Alumno",
      "membership": ""
    },
    {
      "id": "lxwqdyh0sggryp1iea",
      "username": "saaa",
      "password": "lxwqdyh0sggryp1iea",
      "firstname": "",
      "lastname": "",
      "phonenumber": "",
      "email": "",
      "usertype": "Alumno",
      "membership": ""
    },
    {
      "id": "lxwqmjssaquf3uflt7",
      "username": "asasasas",
      "password": "lxwqmjssaquf3uflt7",
      "firstname": "",
      "lastname": "",
      "phonenumber": "",
      "email": "",
      "usertype": "Alumno",
      "membership": ""
    },
    {
      "id": "lxwr2rvja0cos6dx8c",
      "username": "asdasd",
      "password": "lxwr2rvja0cos6dx8c",
      "firstname": "",
      "lastname": "",
      "phonenumber": "",
      "email": "",
      "usertype": "Alumno",
      "membership": ""
    },
    {
      "id": "lxwrmf1b2xpn4l04tf",
      "username": "asdasdasd",
      "password": "lxwrmf1b2xpn4l04tf",
      "firstname": "",
      "lastname": "",
      "phonenumber": "",
      "email": "",
      "usertype": "Alumno",
      "membership": ""
    },
    {
      "id": "lxwsfgc853vi37o78y",
      "username": "tyatas",
      "password": "lxwsfgc853vi37o78y",
      "firstname": "",
      "lastname": "",
      "phonenumber": "",
      "email": "",
      "usertype": "Alumno",
      "membership": ""
    },
    {
      "id": "lxwsiiklc60yi1utwu",
      "username": "maikari",
      "password": "lxwsiiklc60yi1utwu",
      "firstname": "",
      "lastname": "",
      "phonenumber": "",
      "email": "",
      "usertype": "Alumno",
      "membership": ""
    },
    {
      "id": "lxwsm84unka9rqk4yt",
      "username": "kari",
      "password": "lxwsm84unka9rqk4yt",
      "firstname": "",
      "lastname": "",
      "phonenumber": "",
      "email": "",
      "usertype": "Alumno",
      "membership": ""
    },
    {
      "id": "lxwsnn03k6zy5h5e9i",
      "username": "kari",
      "password": "lxwsnn03k6zy5h5e9i",
      "firstname": "",
      "lastname": "",
      "phonenumber": "",
      "email": "",
      "usertype": "Alumno",
      "membership": ""
    },
    {
      "id": "lxwsnv01ajspjwsuel",
      "username": "mikaroi",
      "password": "lxwsnv01ajspjwsuel",
      "firstname": "",
      "lastname": "",
      "phonenumber": "",
      "email": "",
      "usertype": "Alumno",
      "membership": ""
    },
    {
      "id": "lxwsqfdsd4ef6229c0",
      "username": "mikaroi",
      "password": "lxwsqfdsd4ef6229c0",
      "firstname": "",
      "lastname": "",
      "phonenumber": "",
      "email": "",
      "usertype": "Alumno",
      "membership": ""
    },
    {
      "id": "lxwsqyygl5vmtwrjrj",
      "username": "mikaroii",
      "password": "lxwsqyygl5vmtwrjrj",
      "firstname": "",
      "lastname": "",
      "phonenumber": "",
      "email": "",
      "usertype": "Alumno",
      "membership": ""
    },
    {
      "id": "lxwwhvn5nrfd09w06w",
      "username": "Fangos",
      "password": "lxwwhvn5nrfd09w06w",
      "firstname": "",
      "lastname": "",
      "phonenumber": "",
      "email": "",
      "usertype": "Alumno",
      "membership": ""
    },
    {
      "id": "lxwwllr7f16im1kees",
      "username": "asasasas",
      "password": "lxwwllr7f16im1kees",
      "firstname": "",
      "lastname": "",
      "phonenumber": "",
      "email": "",
      "usertype": "Alumno",
      "membership": ""
    },
    {
      "id": "lxwxsa87a7e6ylvggf",
      "username": "jukook",
      "password": "lxwxsa87a7e6ylvggf",
      "firstname": "",
      "lastname": "",
      "phonenumber": "",
      "email": "",
      "usertype": "Alumno",
      "membership": ""
    },
    {
      "id": "lxwy5putv3o6fhywue",
      "username": "Participantesasasa",
      "password": "lxwy5putv3o6fhywue",
      "firstname": "",
      "lastname": "",
      "phonenumber": "",
      "email": "",
      "usertype": "Alumno",
      "membership": ""
    },
    {
      "id": "lxwy8v79494xzm6z9l",
      "username": "kastshe",
      "password": "lxwy8v79494xzm6z9l",
      "firstname": "",
      "lastname": "",
      "phonenumber": "",
      "email": "",
      "usertype": "Alumno",
      "membership": ""
    },
    {
      "id": "lxwyaey0cerpu52vmp",
      "username": "faaaa",
      "password": "lxwyaey0cerpu52vmp",
      "firstname": "",
      "lastname": "",
      "phonenumber": "",
      "email": "",
      "usertype": "Alumno",
      "membership": ""
    },
    {
      "id": "lxwyjlj4dnx2u29bh5",
      "username": "tiii",
      "password": "lxwyjlj4dnx2u29bh5",
      "firstname": "",
      "lastname": "",
      "phonenumber": "",
      "email": "",
      "usertype": "Alumno",
      "membership": ""
    },
    {
      "id": "lxwypy29hwq5al43cj",
      "username": "hjkhjl",
      "password": "lxwypy29hwq5al43cj",
      "firstname": "",
      "lastname": "",
      "phonenumber": "",
      "email": "",
      "usertype": "Alumno",
      "membership": ""
    },
    {
      "id": "lxwyu36ol02lkkz03e",
      "username": "yalediodice",
      "password": "lxwyu36ol02lkkz03e",
      "firstname": "",
      "lastname": "",
      "phonenumber": "",
      "email": "",
      "usertype": "Alumno",
      "membership": ""
    },
    {
      "id": "lxwyxiqasf38zx586c",
      "username": "sakuyo",
      "password": "lxwyxiqasf38zx586c",
      "firstname": "",
      "lastname": "",
      "phonenumber": "",
      "email": "",
      "usertype": "Alumno",
      "membership": ""
    },
    {
      "id": "lxwyyf81biqywm0f2z",
      "username": "assaada",
      "password": "lxwyyf81biqywm0f2z",
      "firstname": "",
      "lastname": "",
      "phonenumber": "",
      "email": "",
      "usertype": "Alumno",
      "membership": ""
    },
    {
      "id": "lxwz5ag57rr8rhfn3g",
      "username": "essadasd",
      "password": "lxwz5ag57rr8rhfn3g",
      "firstname": "",
      "lastname": "",
      "phonenumber": "",
      "email": "",
      "usertype": "Alumno",
      "membership": ""
    },
    {
      "id": "lxwz5v1py2zneohhan",
      "username": "asdasda",
      "password": "lxwz5v1py2zneohhan",
      "firstname": "",
      "lastname": "",
      "phonenumber": "",
      "email": "",
      "usertype": "Alumno",
      "membership": ""
    },
    {
      "id": "lxwz6rndrfbeyvhn14",
      "username": "MiercolesDeNieve",
      "password": "lxwz6rndrfbeyvhn14",
      "firstname": "",
      "lastname": "",
      "phonenumber": "",
      "email": "",
      "usertype": "Alumno",
      "membership": ""
    },
    {
      "id": "lxwz8fh5qxexlc0dpd",
      "username": "hijodekirito",
      "password": "lxwz8fh5qxexlc0dpd",
      "firstname": "",
      "lastname": "",
      "phonenumber": "",
      "email": "",
      "usertype": "Alumno",
      "membership": ""
    },
    {
      "id": "lxwze3gvg1swmjzcgv",
      "username": "toteshimata",
      "password": "lxwze3gvg1swmjzcgv",
      "firstname": "",
      "lastname": "",
      "phonenumber": "",
      "email": "",
      "usertype": "Alumno",
      "membership": ""
    }
  ],
  "Profesores": [],
  "Alumnos": []
}